Metadata-Version: 2.1
Name: yssh
Version: 1.0.0
Summary: ssh tool with expect and multithreading
Home-page: https://github.com/laowangv5/yssh
Author: Yonghang Wang
Author-email: yhang_wang@icloud.com
License: MIT
Keywords: ssh,yssh,myssh,pssh,sshx
Platform: UNKNOWN
Classifier: License :: OSI Approved :: MIT License
